classy_sz.cpython-310-x86_64-linux-gnu.so
classy_sz.libs/libfftw3-376b203f.so.3.6.10
classy_sz.libs/libgomp-a34b3233.so.1.0.0
classy_sz.libs/libgsl-1389c23a.so.27.0.0
classy_sz.libs/libgslcblas-08320ee6.so.0.0.0
classy_sz-0.1.70.post40.dist-info/METADATA
classy_sz-0.1.70.post40.dist-info/WHEEL
classy_sz-0.1.70.post40.dist-info/top_level.txt
classy_sz-0.1.70.post40.dist-info/RECORD
classy_sz-0.1.70.post40.dist-info/licenses/LICENSE
