Metadata-Version: 2.4
Name: classy_sz
Version: 0.1.70.post40
Summary: The class_sz code from https://github.com/CLASS-SZ
Home-page: https://github.com/CLASS-SZ
Author: Boris Bolliet, Ola Kusiak, Fiona McCarthy, Alina Sabyr, Kristen Surrao
Author-email: Boris Bolliet <bb667@cam.ac.uk>
Maintainer-email: Boris Bolliet <bb667@cam.ac.uk>
License: MIT
Project-URL: Homepage, https://github.com/CLASS-SZ
Project-URL: GitHub, https://github.com/CLASS-SZ
License-File: LICENSE
Requires-Dist: classy_szfast>=0.0.25.post22
Dynamic: author
Dynamic: home-page
Dynamic: license-file
